{
    "seo": {
        "publisher": "https://plus.google.com/+lenskart",
        "title": "Lenskart.sg® - Sunglasses, Contact Lens, Eyeglasses, Frames, Buy 1 Get 1 Offer for Gold Members",
        "keywords": "Online shopping, Eyewear, Contact Lenses",
        "xDefault": "https://www.lenskart.sg/",
        "description": "Shop online for Sunglasses, Eyeglasses and Contact Lenses for men & women and Get upto 18% Discount at lenskart.sg.  ✓FREE shipping ✓Cash on Delivery ✓14 Days Return",
        "alternate": {
            "en-sa": "https://www.lenskart.com/en-sa/",
            "en-sg": "https://www.lenskart.sg/",
            "en-us": "https://www.lenskart.com/en-us/",
            "ar-sa": "https://www.lenskart.com/ar-sa/",
            "en-ae": "https://www.lenskart.com/en-ae/"
        },
        "canonical": "https://www.lenskart.sg/"
    },
    "sections": [
        {
            "blockType": "TOP_BLOCK",
            "data": [
                {
                    "data": [
                        {
                            "css": "<style type='text/css'>.dropdown{position:relative;display:inline-block}.dropdown-content{width:94%;margin-left:3%;display:none;position:absolute;background-color:#fff;box-shadow:0px 8px 16px 0px rgba(0, 0, 0, 0.2);z-index:1;border-radius:10px;top:0}.dropdown-content a{color:black;padding:2px 12px;text-decoration:none;display:block;border-bottom:1px solid #eaeaea}.dropdown-content a:hover{background-color:#f4f4f4}.dropdown-content a.top-level:hover{background-color:#fff}.dropdown:hover .dropdown-content{display:block}.widget-title{font-size:15px;color:#8a8888;font-family:'Plus Jakarta Sans-Medium';letter-spacing:0.5px}#categories{width:100%;margin:0 0 0 2.3%}#categories img{width:100%}#categories div.dropdown{width:16%;float:left}.menuitem{width:65%}.menuitem1{width:22%;padding-bottom:13px}.menuitem2 img{width:100% !important;padding-top:15px}.menuitem2{width:4%}.menuitem div:first-child{font-weight:bold;font-size:12px}.menuitem div:last-child, .menuitem1 div:first-child{padding-top:6px;font-size:12px}.menuitem1 div:last-child{padding-top:6px;font-weight:bold;font-size:12px}.menuitem2{color:#37b4c7;font-weight:bold}.menudrop{width:100%;letter-spacing:0.1px}.viewall{color:#37b4c7;font-weight:bold;padding:10px 0;font-size:14px;text-align:left}.menudrop td{vertical-align:baseline}.dropdown-content img{padding:10px 5px 0 0}.dropdown-content .widget-title{padding:5px 0 10px 0}.dropbtn{padding:0 8px;border:1px solid #f5f5f5;border-radius:10px}.dropbtn div{background:#fff;padding:5px;border-radius:10px}.first{border-top:1px solid #efefef}#categories{font-family:'Plus Jakarta Sans-Medium'}.dropTopImg{width:100% !important;padding-top:15px}.dropdown-content a:last-child{border-bottom-left-radius:10px;border-bottom-right-radius:10px}.dropdown a{text-decoration:none !important;color:#000 !important}#content>div>div>div.sectionComponents>div>div:nth-child(1){background:#f5f5f5;padding-top:15px} . {width:90%}</style>",
                            "html": "<center>     <div id='categories justcenter '>         <div class='dropdown'>             <div class='dropbtn'>                 <div><img class='mainicon' src='https://static1.lenskart.com/media/desktop/img/17-jan-25/a/sg-top-n%201.png' />                     <div class='widget-title'>Eyeglasses</div>                 </div>             </div>             <div class='dropdown-content menumargin'><a href='sg/eyeglasses/collections/all-eyeglasses.html'                     data-creative-name='TYPE_BANNER_MINI' data-promotion-id='top_grid_eyeglasses'                     data-promotion-name='top grid eyeglasses' class='top-level'><img class='dropTopImg'                         src='https://static1.lenskart.com/media/desktop/img/17-jan-25/a/sg-top-n%201.png' />                     <div class='widget-title'>Eyeglasses</div>                 </a></div>         </div>         <div class='dropdown'>             <div class='dropbtn'>                 <div><img class='mainicon'                         src='https://static1.lenskart.com/media/desktop/img/17-jan-25/a/sg-top-n%202.png' />                     <div class='widget-title'>Clip-On Glasses</div>                 </div>             </div>             <div class='dropdown-content menumargin'><a href='/sg/eyeglasses/collections/clip-on-eyeglasses.html'                     class='top-level' data-creative-name='TYPE_BANNER_MINI'                     data-promotion-id='top_grid_clip_on_glasses' data-promotion-name='top grid clipon glasses'><img                         class='dropTopImg'                         src='https://static1.lenskart.com/media/desktop/img/17-jan-25/a/sg-top-n%202.png' />                     <div class='widget-title'>Clip-On Glasses</div>                 </a></div>         </div>         <div class='dropdown'>             <div class='dropbtn'>                 <div><img class='mainicon' src='https://static1.lenskart.com/media/desktop/img/17-jan-25/a/sg-top-n%203.png' />                     <div class='widget-title'>Contact Lenses</div>                 </div>             </div>             <div class='dropdown-content menumargin'><a href='/sg/contact-lenses/collections/cl-collection.html'                     class='top-level' data-creative-name='TYPE_BANNER_MINI'                     data-promotion-id='top_grid_contact_lens' data-promotion-name='top grid contact lens'><img                         class='dropTopImg' src='https://static1.lenskart.com/media/desktop/img/17-jan-25/a/sg-top-n%203.png' />                     <div class='widget-title'>Contact Lenses</div>                 </a><a class='first getGaData' data-event='Banner Clicks' data-category='Banner Clicks'                     data-action='MENU_CONTACT_LENS' data-label='all_contact_lens'                     href='/sg/contact-lenses/collections/cl-collection.html' data-creative-name='TYPE_BANNER_MINI'                     data-promotion-id='top_grid_cl_collection' data-promotion-name='top grid cl collection'>                     <table class='menudrop'>                         <tr>                             <td class='menuitem'>                                 <div>All Contact Lens</div>                             </td>                             <td class='menuitem1'>                                 <div>Starting</div>                                 <div>$10</div>                             </td>                         </tr>                     </table>                 </a><a class='getGaData' data-event='Banner Clicks' data-category='Banner Clicks'                     data-action='MENU_CONTACT_LENS' data-label='new_user_trial'                     href='/sg/contact-lenses/promotions/aquacolor-trial.html' data-creative-name='TYPE_BANNER_MINI'                     data-promotion-id='top_grid_aquacolor_trial' data-promotion-name='top grid aqualcolor-trial'>                     <table class='menudrop'>                         <tr>                             <td class='menuitem'>                                 <div>New User Trial</div>                             </td>                             <td class='menuitem1'>                                 <div>Starting</div>                                 <div>$5</div>                             </td>                         </tr>                     </table>                 </a><a class='getGaData' data-event='Banner Clicks' data-category='Banner Clicks'                     data-action='MENU_CONTACT_LENS' data-label='contact_lens_solution'                     href='sg/accessories/contact-lens-solution.html' data-creative-name='TYPE_BANNER_MINI'                     data-promotion-id='top_grid_cl_solution' data-promotion-name='top grid cl solution'>                     <table class='menudrop'>                         <tr>                             <td class='menuitem'>                                 <div>Contact Lens Solution</div>                             </td>                             <td class='menuitem1'>                                 <div>Starting</div>                                 <div>$5</div>                             </td>                         </tr>                     </table>                 </a></div>         </div>         <div class='dropdown'>             <div class='dropbtn'>                 <div><img src='https://static1.lenskart.com/media/desktop/img/17-jan-25/a/sg-top-n%205.png'                         class='mainicon' />                     <div class='widget-title'>Kids Glasses</div>                 </div>             </div>             <div class='dropdown-content menumargin'><a href='/sg/eyeglasses/kids-eyeglasses.html'                     class='top-level' data-creative-name='TYPE_BANNER_MINI'                     data-promotion-id='top_grid_airwrap_eyeglasses'                     data-promotion-name='top grid airwrap eyeglasses'><img class='dropTopImg'                         src='https://static1.lenskart.com/media/desktop/img/17-jan-25/a/sg-top-n%205.png' />                     <div class='widget-title'>Kids Glasses</div>                 </a></div>         </div>         <div class='dropdown'>             <div class='dropbtn'>                 <div><img class='mainicon' src='https://static1.lenskart.com/media/desktop/img/17-jan-25/a/sg-top-n%207.png' />                     <div class='widget-title'>Sunglasses</div>                 </div>             </div>             <div class='dropdown-content menumargin'><a href='/sg/sunglasses/all-sunglasses.html' class='top-level'                     data-creative-name='TYPE_BANNER_MINI' data-promotion-id='top_grid_sunglasses'                     data-promotion-name='top grid sunglasses'><img class='dropTopImg'                         src='https://static1.lenskart.com/media/desktop/img/17-jan-25/a/sg-top-n%207.png' />                     <div class='widget-title'>Sunglasses</div>                 </a></div>         </div>         <div class='dropdown'>             <div class='dropbtn'>                 <div><img class='mainicon' src='https://static1.lenskart.com/media/desktop/img/17-jan-25/a/sg-top-n%208.png' />                     <div class='widget-title'>Progressive</div>                 </div>             </div>             <div class='dropdown-content menumargin'><a href='/sg/eyeglasses/collections/progressive.html'                     class='top-level' data-creative-name='TYPE_BANNER_MINI'                     data-promotion-id='top_grid_progressive_eyeglasses'                     data-promotion-name='top grid progressive eyeglasses'><img class='dropTopImg'                         src='https://static1.lenskart.com/media/desktop/img/17-jan-25/a/sg-top-n%208.png' />                     <div class='widget-title'>Progressive</div>                 </a></div>         </div>     </div> </center>"
                        }
                    ],
                    "type": "TYPE_BANNER"
                }
            ],
            "bottomSpace": "15"
        },
        {
            "data": [
                {
                    "settings": {
                        "speed": 800000,
                        "slidesToShow": 1,
                        "adaptiveHeight": true,
                        "easing": "linear",
                        "autoplay": false,
                        "infinite": true,
                        "dots": false,
                        "arrows": true,
                        "lazyLoad": false,
                        "fade": false,
                        "pauseOnHover": true,
                        "autoplaySpeed": 200000
                    },
                    "class": "w3-content justcenter w3-display-container ",
                    "type": "TYPE_BANNER_CAROUSEL",
                    "data": [
                        {
                            "html": "<a class='getGaData' data-event='Banner Clicks' data-category='Banner Clicks' data-action='CAROUSEL' data-label='home-new-carousel-batman' href='https://www.lenskart.sg/sg/eyewear/collections/the-dark-knight-x-lenskart.html' data-creative-name='TYPE_BANNER' data-promotion-id='home-new-carousel-batman' data-promotion-name='home new carousel switch flipup'><img class='mySlides' src='https://static5.lenskart.com/media/uploads/WEB_BANNER_4_20062025_rat.png' style='width:100%' /></a>"
                        },
                        {
                            "html": "<a class='getGaData' data-event='Banner Clicks' data-category='Banner Clicks' data-action='CAROUSEL' data-label='home-new-carousel-switch-flipup' href='https://www.lenskart.sg/sg/eyeglasses/collections/switch-premium.html' data-creative-name='TYPE_BANNER' data-promotion-id='home-new-carousel-switch-flipup' data-promotion-name='home new carousel switch flipup'><img class='mySlides' src='https://static5.lenskart.com/media/uploads/WEB-BANNER-1-switch-new.gif' style='width:100%' /></a>"
                        },
                        {
                            "html": "<a class='getGaData' data-event='Banner Clicks' data-category='Banner Clicks' data-action='CAROUSEL' data-label='home-new-carousel-urban-metal' href='https://www.lenskart.sg/sg/eyeglasses/collections/urban-metals.html' data-creative-name='TYPE_BANNER' data-promotion-id='home-new-carousel-urban-metal' data-promotion-name='home new carousel urban switch'><img class='mySlides' src='https://static5.lenskart.com/media/uploads/Copy_of_Hero_Banner-desktop.jpg' style='width:100%' /></a>"
                        },
                        {
                            "html": "<a class='getGaData' data-event='Banner Clicks' data-category='Banner Clicks' data-action='CAROUSEL' data-label='home-new-carousel-bitz' href='https://www.lenskart.sg/lenskart-bitz' data-creative-name='TYPE_BANNER' data-promotion-id='home-new-carousel-bitz' data-promotion-name='home new carousel bitz'><img class='mySlides' src='https://static5.lenskart.com/media/uploads/Web_Banner-SG-040325.gif' style='width:100%' /></a>"
                        },
                        {
                            "html": "<a class='getGaData' data-event='Banner Clicks' data-category='Banner Clicks' data-action='CAROUSEL' data-label='home-new-carousel-on-the-go' href='https://www.lenskart.sg/sg/eyeglasses/collections/on-the-go.html' data-creative-name='TYPE_BANNER' data-promotion-id='home-new-carousel-on-the-go' data-promotion-name='home new carousel on the go'><img class='mySlides' src='https://static5.lenskart.com/media/uploads/WEB-BANNER-1-0602.gif' style='width:100%' /></a>"
                        },
                        {
                            "html": "<a class='getGaData' data-event='Banner Clicks' data-category='Banner Clicks' data-action='CAROUSEL' data-label='home-new-carousel-iconic' href='https://www.lenskart.sg/sg/eyewear/collections/iconic-all-ways.html' data-creative-name='TYPE_BANNER' data-promotion-id='home-new-carousel-iconic' data-promotion-name='home new carousel iconic'><img class='mySlides' src='https://static5.lenskart.com/media/uploads/WEB_BANNER-10march.png' style='width:100%' /></a>"
                        },
                        {
                            "html": "<a class='getGaData' data-event='Banner Clicks' data-category='Banner Clicks' data-action='CAROUSEL' data-label='home-new-carousel-clear-edit' href='https://www.lenskart.sg/sg/eyeglasses/collections/the-clear-edit.html' data-creative-name='TYPE_BANNER' data-promotion-id='home-new-carousel-clear' data-promotion-name='home new carousel clear'><img class='mySlides' src='https://static5.lenskart.com/media/uploads/web-clear-edit24.png' style='width:100%' /></a>"
                        },
                        {
                            "html": "<a class='getGaData' data-event='Banner Clicks' data-category='Banner Clicks' data-action='CAROUSEL' data-label='home-new-carousel-profit' href='https://www.lenskart.sg/sg/eyeglasses/collections/pro-fit.html' data-creative-name='TYPE_BANNER' data-promotion-id='home-new-carousel-profit' data-promotion-name='home new carousel profit'><img class='mySlides' src='https://static1.lenskart.com/media/desktop/img/May24/pro-fit-lenskart-air/Desktop-Bannerpro_fit040624.gif' style='width:100%' /></a>"
                        },
                        {
                            "html": "<a class='getGaData' data-event='Banner Clicks' data-category='Banner Clicks' data-action='CAROUSEL' data-label='home-new-carousel-swap-fit' href='https://www.lenskart.sg/sg/eyeglasses/collections/swapfits.html' data-creative-name='TYPE_BANNER' data-promotion-id='home-new-carousel-swap-fit' data-promotion-name='home new carousel swapfit'><img class='mySlides' src='https://static5.lenskart.com/media/uploads/Web-Banner-25-swap-fit.gif' style='width:100%' /></a>"
                        },
                        {
                            "html": "<a class='getGaData' data-event='Banner Clicks' data-category='Banner Clicks' data-action='CAROUSEL' data-label='home-new-carousel-kseries' href='https://www.lenskart.sg/sg/eyeglasses/collections/k-series.html' data-creative-name='TYPE_BANNER' data-promotion-id='home-new-carousel-kseries' data-promotion-name='home new carousel kseries'><img class='mySlides' src='https://static5.lenskart.com/media/uploads/web_page_bannerseriesnew.gif' style='width:100%' /></a>"
                        },
                        {
                            "html": "<a class='getGaData' data-event='Banner Clicks' data-category='Banner Clicks' data-action='CAROUSEL' data-label='home-new-carousel-creatr' href='https://www.lenskart.sg/sg/eyeglasses/collections/hooper-creatr.html' data-creative-name='TYPE_BANNER' data-promotion-id='home-new-carousel-creatr' data-promotion-name='home new carousel creatr'><img class='mySlides' src='https://static5.lenskart.com/media/uploads/creaTr-web-banner-24-20.gif' style='width:100%' /></a>"
                        }
                    ],
                    "css": ".w3-content .slick-slide {padding:0;} .mySlides {display:none;}.w3-content {margin-left:auto;margin-right:auto} .w3-display-container{position:relative} .w3-black {color:#fff!important;background-color:#000} .w3-display-left{position:absolute;top:50%;left:2%;transform:translate(0%,-50%);-ms-transform:translate(-0%,-50%)} .w3-display-right{position:absolute;top:50%;right:2%;transform:translate(0%,-50%);-ms-transform:translate(0%,-50%)}  .sliderbutton{padding:10px 15px;font-size:45px;background:none;border:none;} .sliderbutton:hover{font-size:50px} .w85 {width:85%;} .w3-display-container.slider-main.carousel-comp-slider{width:calc(100% + 30px) !important;margin-left: -15px;margin-right: -15px;} .w3-display-container .slick-arrow.slick-prev, .w3-display-container .slick-arrow.slick-next{padding: 10px 15px;font-size: 45px;background: none!important;border: none;} .w3-display-container .slick-arrow.slick-prev{left:2%;} .w3-display-container .slick-arrow.slick-next:before, .w3-display-container .slick-arrow.slick-prev:before{display: block;color: #fff;transform: translateY(50%);} .w3-display-container .slick-arrow.slick-prev:before{content: '❮';} .w3-display-container .slick-arrow.slick-next:before{content: '❯';transform: translate(-13px, 50%)} .w3-display-container .slick-arrow.slick-next{right:2%;} .w3-display-container .slick-arrow.slick-next:hover, .w3-display-container .slick-arrow.slick-prev:hover{font-size: 50px;}"
                }
            ],
            "bottomSpace": "20",
            "blockType": "TOP_BLOCK"
        },
        {
            "data": [
                {
                    "type": "TYPE_BANNER",
                    "data": [
                        {
                            "html": "<center><div class='our-brands-sect flex w100 mt35'><a class='getGaData' data-event='Banner Clicks' data-category='Banner Clicks' data-action='black-friday' data-label='black-friday' data-creative-name='TYPE_BANNER' data-promotion-id='lkfiesta' data-promotion-name='black-friday 151124' href='https://www.lenskart.sg/sg/eyeglasses/promotions/new-user-offer.html'><img src='https://static1.lenskart.com/media/desktop/img/June25/SG-Sale/Desktop%20Banner.png' /></a></div></center>"
                        }
                    ]
                }
            ],
            "blockType": "TOP_BLOCK",
            "bottomSpace": "10"
        },
        {
            "data": [
                {
                    "type": "TYPE_BANNER",
                    "data": [
                        {
                            "html": "<center><h4 class='font-head mt70'>FREE LENS REPLACEMENT AT STORES</h4><div class='our-brands-sect flex w100 mt35'><a class='getGaData' data-event='Banner Clicks' data-category='Banner Clicks' data-action='vision-for-all' data-label='vision-for-all' data-creative-name='TYPE_BANNER' data-promotion-id='vision-for-all' data-promotion-name='vision for all 291123' href='https://www.lenskart.sg/lens-replacement-at-store.html'><img src='https://static5.lenskart.com/media/uploads/1920x520-replace-sg.png' /></a></div></center>"
                        }
                    ]
                }
            ],
            "blockType": "TOP_BLOCK",
            "bottomSpace": "10"
        },
        {
            "bottomSpace": "10",
            "data": [
                {
                    "type": "TYPE_BANNER",
                    "data": [
                        {
                            "html": "<center><h4 class='font-head mt70'>TRENDING NOW</h4><div class='perfect-fit-sect flex w100 mt35 justcenter'><div class='mr2p'><a href='/sg/eyeglasses/collections/best-sellers.html'><img src='https://static1.lenskart.com/media/desktop/img/SG/eyeglasses_collection.png'/></a></div><div class='mr2p'><a href='/sg/eyeglasses/collections/clip-on-eyeglasses.html'><img src='https://static1.lenskart.com/media/desktop/img/SG/air_switch/Secondary-banners_03_min.gif'/></a></div><div class='mr2p'><a href='/sg/eyeglasses/collections/k-series.html'><img src='https://static1.lenskart.com/media/desktop/img/SG/k-pop/K-pop.png'/></a></div><div><a href='/sg/eyeglasses/kids-eyeglasses.html'><img src='https://static1.lenskart.com/media/desktop/img/SG/kids_collection.png'/></a></div></div></center>",
                            "css": "<style>h4 { display: flex; flex-direction: row; width:100%;color:black;} h4:before, h4:after { content: ''; flex: 1 1; border-bottom: 1px solid #cfcdcd; margin: auto 15px; } .flex {display:flex} .mt35{margin-top:35px} .mt70{margin-top:80px} .w80 {width:80%} .pt15 {padding-top:15px;} .pb15 {padding-bottom:15px;} .pl15 {padding-left:15px;} .pr15 {padding-right:15px;} .font-head {font-family:'Plus Jakarta Sans-Medium';letter-spacing:0.5px;font-size:30px;} .w92 {width:92%} .w50 {width:50%} .pl7 {padding-left:7.5px} .pr7 {padding-right:7.5px} .w100 {width:100%} .catSlider_btn {display:none} .catSlider {border:0} .bottom-b {border-bottom: 1px solid #cfcdcd;} .catSlider {width:100%;margin-left:5%} .justcenter, .our-brands-sect {justify-content:center} .dropdown {width:16%} .home {width:100%;max-width:1920px;margin: 0 auto;} .mr2p {margin-right:2%} .mrt2p {margin-top:2%} .mb70 {margin-bottom:70px}</style>"
                        }
                    ]
                }
            ],
            "blockType": "TOP_BLOCK"
        },
        {
            "data": [
                {
                    "data": [
                        {
                            "html": "<center><h4 class='font-head mt70'>OUR BRANDS</h4><div class='our-brands-sect flex w100 mt35'><a class='getGaData' data-event='Banner Clicks' data-category='Banner Clicks' data-action='OUR_BRANDS_TOP_BANNER' data-label='1_vincent_chase' href='/sg/eyeglasses/brands/vincent-chase-eyeglasses.html'><img src='https://static1.lenskart.com/media/desktop/img/Apr22/Brands-1.jpg' /></a></div></center>"
                        }
                    ],
                    "type": "TYPE_BANNER"
                }
            ],
            "bottomSpace": "10",
            "blockType": "TOP_BLOCK"
        },
        {
            "bottomSpace": "10",
            "data": [
                {
                    "type": "TYPE_BANNER",
                    "data": [
                        {
                            "css": "<style>.prod-row-left {text-align:left;} .prod-row-right {text-align:right;} .fs22 {font-size:22px;} .fs17 {font-size:17px;} .catSlider .carousel-comp-slider {margin:0 !important} .slider-main {width:88% !important} .catSlider_desc {display:none}</style>",
                            "html": "<center><div class='flex w80 mt35 bottom-b'><div class='prod-row-left w50 fs22'>EYEGLASSES</div><div class='prod-row-right w50 fs17'><a class='getGaData' data-event='Banner Clicks' data-category='Banner Clicks' data-action='OUR_BRANDS_VINCENT_CHASE_EYEGLASSES' data-label='1_view_range' href='/sg/eyeglasses/brands/vincent-chase-eyeglasses.html'>View Range</a></div></div></center>"
                        }
                    ]
                }
            ],
            "blockType": "TOP_BLOCK"
        },
        {
            "bottomSpace": "20",
            "data": [
                {
                    "data": {
                        "dtmCat": "Eyeglasses",
                        "catId": 10796,
                        "dtm": "Collections|Best Seller VC Eye",
                        "gaObj": {
                            "event": "Banner_Clicks",
                            "category": "Banner_Clicks",
                            "label": "Best Seller VC Eye",
                            "action": "TYPE_CATEGORY_CAROUSEL"
                        },
                        "gaPromotionObj": {
                            "itemlistName": "test-list-2",
                            "creativeName": "TYPE_BANNER_CAROUSEL",
                            "promotionId": "our_vc_view_all_below_grid",
                            "itemlistId": "test-list-1",
                            "promotionName": "vc our brand view all 03072023"
                        }
                    },
                    "type": "TYPE_CATEGORY_CAROUSEL"
                }
            ]
        },
        {
            "bottomSpace": "10",
            "data": [
                {
                    "data": [
                        {
                            "html": "<center><div class='flex w80 mt35 bottom-b'><div class='prod-row-left w50 fs22'>SUNGLASSES</div><div class='prod-row-right w50 fs17'><a class='getGaData' data-event='Banner Clicks' data-category='Banner Clicks' data-action='OUR_BRANDS_VINCENT_CHAISE_SUNGLASSES' data-label='2_view_range' href='/sg/sunglasses/brands/vincent-chase-sunglasses.html'>View Range</a></div></div></center>",
                            "css": "<style>.prod-row-left {text-align:left;} .prod-row-right {text-align:right;} .fs22 {font-size:22px;} .fs17 {font-size:17px;} .mb35 {margin-bottom:35px;} </style>"
                        }
                    ],
                    "type": "TYPE_BANNER"
                }
            ],
            "blockType": "TOP_BLOCK"
        },
        {
            "data": [
                {
                    "type": "TYPE_CATEGORY_CAROUSEL",
                    "data": {
                        "dtm": "Collections|Best Seller VC Sun",
                        "catId": 10771,
                        "dtmCat": "Eyeglasses",
                        "gaObj": {
                            "category": "Banner_Clicks",
                            "action": "TYPE_CATEGORY_CAROUSEL",
                            "label": "Best Seller VC Sun",
                            "event": "Banner_Clicks"
                        }
                    }
                }
            ],
            "bottomSpace": "20"
        },
        {
            "bottomSpace": "10",
            "data": [
                {
                    "data": [
                        {
                            "html": "<center><div class='our-brands-sect flex w100 mt35'><a class='getGaData' data-event='Banner Clicks' data-category='Banner Clicks' data-action='OUR_BRANDS_TOP_BANNER' data-label='2_john_jacobs' href='sg/eyeglasses/brands/john-jacobs-eyeglasses.html'><img src='https://static1.lenskart.com/media/desktop/img/SG/jj_new_logo/Desktop_HP_JJ_09012023_1.jpg' /></a></div></center>"
                        }
                    ],
                    "type": "TYPE_BANNER"
                }
            ],
            "blockType": "TOP_BLOCK"
        },
        {
            "blockType": "TOP_BLOCK",
            "data": [
                {
                    "type": "TYPE_BANNER",
                    "data": [
                        {
                            "css": "<style>.prod-row-left {text-align:left;} .prod-row-right {text-align:right;} .fs22 {font-size:22px;} .fs17 {font-size:17px;}</style>",
                            "html": "<center><div class='flex w80 mt35 bottom-b'><div class='prod-row-left w50 fs22'>EYEGLASSES</div><div class='prod-row-right w50 fs17'><a class='getGaData' data-event='Banner Clicks' data-category='Banner Clicks' data-action='OUR_BRANDS_JOHN_JACOBS_EYEGLASSES' data-label='1_view_range' href='sg/eyeglasses/brands/john-jacobs-eyeglasses.html'>View Range</a></div></div></center>"
                        }
                    ]
                }
            ],
            "bottomSpace": "10"
        },
        {
            "bottomSpace": "20",
            "data": [
                {
                    "type": "TYPE_CATEGORY_CAROUSEL",
                    "data": {
                        "gaObj": {
                            "action": "TYPE_CATEGORY_CAROUSEL",
                            "event": "Banner_Clicks",
                            "category": "Banner_Clicks",
                            "label": "Best Seller John Jacobs Eye"
                        },
                        "dtmCat": "Eyeglasses",
                        "catId": 10848,
                        "dtm": "Collections|John Jacobs Eye"
                    }
                }
            ]
        },
        {
            "bottomSpace": "10",
            "blockType": "TOP_BLOCK",
            "data": [
                {
                    "data": [
                        {
                            "css": "<style>.prod-row-left {text-align:left;} .prod-row-right {text-align:right;} .fs22 {font-size:22px;} .fs17 {font-size:17px;}</style>",
                            "html": "<center><div class='flex w80 mt35 bottom-b'><div class='prod-row-left w50 fs22'>SUNGLASSES</div><div class='prod-row-right w50 fs17'><a class='getGaData' data-event='Banner Clicks' data-category='Banner Clicks' data-action='OUR_BRANDS_JOHN_JACOBS_SUNGLASSES' data-label='2_view_range' href='/sg/sunglasses/brands/john-jacobs-sunglasses.html'>View Range</a></div></div></center>"
                        }
                    ],
                    "type": "TYPE_BANNER"
                }
            ]
        },
        {
            "data": [
                {
                    "data": {
                        "dtmCat": "Eyeglasses",
                        "gaObj": {
                            "label": "Best Seller John Jacobs Sunglasses",
                            "event": "Banner_Clicks",
                            "category": "Banner_Clicks",
                            "action": "TYPE_CATEGORY_CAROUSEL"
                        },
                        "dtm": "Collections|John Jacobs Sunglasses",
                        "catId": 10772
                    },
                    "type": "TYPE_CATEGORY_CAROUSEL"
                }
            ],
            "bottomSpace": "20"
        },
        {
            "data": [
                {
                    "data": [
                        {
                            "html": "<center><div class='our-brands-sect flex w100 mt35'><a class='getGaData' data-event='Banner Clicks' data-category='Banner Clicks' data-action='OUR_BRANDS_TOP_BANNER' data-label='3_lenskart_air' href='/sg/eyeglasses/brands/lenskart-air-eyeglasses.html'><img src='https://static1.lenskart.com/media/desktop/img/Apr22/Brands-Air.jpg' /></a></div></center>"
                        }
                    ],
                    "type": "TYPE_BANNER"
                }
            ],
            "bottomSpace": "10",
            "blockType": "TOP_BLOCK"
        },
        {
            "data": [
                {
                    "type": "TYPE_BANNER",
                    "data": [
                        {
                            "css": "<style>.prod-row-left {text-align:left;} .prod-row-right {text-align:right;} .fs22 {font-size:22px;} .fs17 {font-size:17px;}</style>",
                            "html": "<center><div class='flex w80 mt35 bottom-b'><div class='prod-row-left w50 fs22'>EYEGLASSES</div><div class='prod-row-right w50 fs17'><a class='getGaData' data-event='Banner Clicks' data-category='Banner Clicks' data-action='OUR_BRANDS_LENSKART_AIR_EYEGLASSES' data-label='1_view_range' href='/sg/eyeglasses/brands/lenskart-air-eyeglasses.html'>View Range</a></div></div></center>"
                        }
                    ]
                }
            ],
            "blockType": "TOP_BLOCK",
            "bottomSpace": "10"
        },
        {
            "data": [
                {
                    "type": "TYPE_CATEGORY_CAROUSEL",
                    "data": {
                        "gaObj": {
                            "label": "Lenskart Air",
                            "action": "TYPE_CATEGORY_CAROUSEL",
                            "category": "Banner_Clicks",
                            "event": "Banner_Clicks"
                        },
                        "dtmCat": "Eyeglasses",
                        "dtm": "Collections|Lenskart Air Eye",
                        "catId": 10770
                    }
                }
            ],
            "bottomSpace": "20"
        },
        {
            "data": [
                {
                    "type": "TYPE_BANNER",
                    "data": [
                        {
                            "html": "<center><div class='our-brands-sect flex w100 mt35'><a class='getGaData' data-event='Banner Clicks' data-category='Banner Clicks' data-action='OUR_BRANDS_TOP_BANNER' data-label='5_hooper_glasses_for_kids' href='/sg/eyeglasses/kids-eyeglasses.html'><img src='https://static1.lenskart.com/media/desktop/img/SG/Kids/desk_home.png' /></a></div></center>"
                        }
                    ]
                }
            ],
            "bottomSpace": "10",
            "blockType": "TOP_BLOCK"
        },
        {
            "blockType": "TOP_BLOCK",
            "bottomSpace": "10",
            "data": [
                {
                    "data": [
                        {
                            "css": "<style>.prod-row-left {text-align:left;} .prod-row-right {text-align:right;} .fs22 {font-size:22px;} .fs17 {font-size:17px;}</style>",
                            "html": "<center><div class='flex w80 mt35 bottom-b'><div class='prod-row-left w50 fs22'>WITH POWER COMPUTER BLU LENSES</div><div class='prod-row-right w50 fs17'><a class='getGaData' data-event='Banner Clicks' data-category='Banner Clicks' data-action='OUR_BRANDS_LENSKART_KIDS_WITH_POWER_COMPUTER_BLU_LENSES' data-label='1_view_range' href='/sg/eyeglasses/kids-eyeglasses.html'>View Range</a></div></div></center>"
                        }
                    ],
                    "type": "TYPE_BANNER"
                }
            ]
        },
        {
            "data": [
                {
                    "type": "TYPE_CATEGORY_CAROUSEL",
                    "data": {
                        "catId": 10789,
                        "dtm": "Collections|Kids Eyeglasses",
                        "dtmCat": "Eyeglasses",
                        "gaObj": {
                            "event": "Banner_Clicks",
                            "action": "TYPE_CATEGORY_CAROUSEL",
                            "category": "Banner_Clicks",
                            "label": "Kids Eyeglasses"
                        }
                    }
                }
            ],
            "bottomSpace": "20"
        },
        {
            "data": [
                {
                    "data": [
                        {
                            "html": "<center><div class='flex w100'><div class='mr2p mrt2p w50'><img src='https://static1.lenskart.com/media/desktop/img/Apr22/Cal_expert-desktop.jpg' /></div><div class='mrt2p w50'><a href='https://api.whatsapp.com/send?phone=6597222210&text=Hi Lenskart, help me get started!'><img src='https://static1.lenskart.com/media/desktop/img/Apr22/Chat-desktop-.jpg' /></a></div></div></center>"
                        }
                    ],
                    "type": "TYPE_BANNER"
                }
            ],
            "blockType": "TOP_BLOCK",
            "bottomSpace": "10"
        },
        {
            "bottomSpace": "10",
            "data": [
                {
                    "data": [
                        {
                            "html": "<style>.insimg {width:16.6%} .insimg img {padding:2%}</style><center><h4 class='font-head mt70'>Join The Lenskart Tribe</h4><div class='w100'><a href='https://www.instagram.com/lenskartsg/?hl=en'><div style='display:flex'><div class='insimg'><img src='https://static1.lenskart.com/media/desktop/img/Apr22/Lenskart-Homepage-social-ig-1.jpg' /></div><div class='insimg'><img src='https://static1.lenskart.com/media/desktop/img/Apr22/Lenskart-Homepage-social-ig-2.jpg' /></div><div class='insimg'><img src='https://static1.lenskart.com/media/desktop/img/Apr22/Lenskart-Homepage-social-ig-3.jpg' /></div><div class='insimg'><img src='https://static1.lenskart.com/media/desktop/img/Apr22/Lenskart-Homepage-social-ig-4.jpg' /></div><div class='insimg'><img src='https://static1.lenskart.com/media/desktop/img/Apr22/Lenskart-Homepage-social-ig-5.jpg' /></div><div class='insimg'><img src='https://static1.lenskart.com/media/desktop/img/Apr22/Lenskart-Homepage-social-ig-6.jpg' /></div></div></a></div></center>"
                        }
                    ],
                    "type": "TYPE_BANNER"
                }
            ],
            "blockType": "TOP_BLOCK"
        }
    ],
    "footers": [
        {
            "bottomSpace": "0",
            "data": [
                {
                    "type": "TYPE_STATIC_HTML",
                    "data": [
                        {
                            "css": "<style>.txt-strong{ font-family: 'Plus Jakarta Sans-Bold'; }.eyewer-text{ color: #484848; padding:20px 15px 0px 15px; }.eyewer-text p{ font-size: 13px; font-family: 'Plus Jakarta Sans-Medium'; line-height: 20px;.eyewer-text h1{ font-size: 2em; }</style>",
                            "html": "<div class=\"container-fluid\"><div class=\"eyewer-text\"><h1 class=\"txt-strong\">Buy The Best Eyewear From Lenskart</h1><p>Lenskart is the leading e-commerce portal for eyewear. It has revolutionised the eyewear industry in the country with its omni-channel approach. From an ever-growing number of offline stores across major cities in the country to innovative integration of technology while purchasing online, Lenskart caters to every customer with several deals and offers.</p><p>A one-stop online solution for purchasing eyewear and its accessories, Lenskart delivers them right at your doorstep with convenient methods of payment. <a href=\"//sg/sunglasses/all-sunglasses.html\">Sunglasses</a> as well as <a href=\"/sg/eyeglasses.html\">eyeglasses</a> are available for men and women in a diverse array of styles and trendy colours.</p></p></div></div>"
                        }
                    ]
                }
            ]
        }
    ]
}